{
    "label": "Cleaning",
    "items": [
        {
            "id": "cleaning_0",
            "name_english": "Bleach",
            "name_espa_ol": "Cloro"
        },
        {
            "id": "cleaning_1",
            "name_english": "Dish Detergent (dawn)",
            "name_espa_ol": "Detergente para platos (Dawn)"
        },
        {
            "id": "cleaning_2",
            "name_english": "Floor cleaner (fabuloso purple)",
            "name_espa_ol": "Limpiador de pisos (Fabuloso morado)"
        },
        {
            "id": "cleaning_3",
            "name_english": "Scrubber Stainless Steel 12/1 ct.",
            "name_espa_ol": "Fibra de acero inoxidable 12/1 ct."
        },
        {
            "id": "cleaning_4",
            "name_english": "Dining Room Sanitizer",
            "name_espa_ol": "Sanitizante para comedor"
        },
        {
            "id": "cleaning_5",
            "name_english": "Stainless Steel cleaner",
            "name_espa_ol": "Limpiador para acero inoxidable"
        },
        {
            "id": "cleaning_6",
            "name_english": "Magic Eraser",
            "name_espa_ol": "Borrador mágico"
        },
        {
            "id": "cleaning_7",
            "name_english": "Window cleaner",
            "name_espa_ol": "Limpiavidrios"
        }
    ]
}